neurotorchmz/__init__.py
neurotorchmz/__main__.py
neurotorchmz/core/__init__.py
neurotorchmz/core/api.py
neurotorchmz/core/events.py
neurotorchmz/core/logs.py
neurotorchmz/core/plugin_manager.py
neurotorchmz/core/resources.py
neurotorchmz/core/serialize.py
neurotorchmz/core/session.py
neurotorchmz/core/settings.py
neurotorchmz/core/task_system.py
neurotorchmz/gui/__init__.py
neurotorchmz/gui/events.py
neurotorchmz/gui/tab1.py
neurotorchmz/gui/tab2.py
neurotorchmz/gui/tab3.py
neurotorchmz/gui/tabAnalysis.py
neurotorchmz/gui/tabWelcome.py
neurotorchmz/gui/window.py
neurotorchmz/gui/components/general.py
neurotorchmz/gui/components/treeview.py
neurotorchmz/plugins/pyimage_j/__init__.py
neurotorchmz/plugins/pyimage_j/pyimagej.py
neurotorchmz/plugins/trace_selector/__init__.py
neurotorchmz/plugins/trace_selector/trace_selector.py
neurotorchmz/resources/neurotorch_coverimage_4.webp
neurotorchmz/resources/neurotorch_logo.ico
neurotorchmz/resources/strings.json
neurotorchmz/utils/denoising.py
neurotorchmz/utils/image.py
neurotorchmz/utils/signal_detection.py
neurotorchmz/utils/synapse_detection.py
neurotorchmz/utils/synapse_detection_integration.py
neurotorchmz-25.9.6.dist-info/METADATA
neurotorchmz-25.9.6.dist-info/WHEEL
neurotorchmz-25.9.6.dist-info/licenses/LICENSE
neurotorchmz-25.9.6.dist-info/RECORD
