Metadata-Version: 2.4
Name: Neurotorchmz
Version: 25.9.6
Summary: Neurotorch is a tool designed to extract regions of synaptic activity in neurons tagges with iGluSnFR, but is in general capable to find any kind of local brightness increase due to synaptic activity
Project-URL: Homepage, https://github.com/andreasmz/neurotorch
Project-URL: Repository, https://github.com/andreasmz/neurotorch
Project-URL: Issues, https://github.com/andreasmz/neurotorch/issues
Project-URL: Documentation, https://andreasmz.github.io/neurotorch/
Author: Andreas Brilka
License-Expression: MIT
License-File: LICENSE
Keywords: glutamate,iGluSnFR,neurons,neurotorch,python,synapses
Classifier: Development Status :: 4 - Beta
Classifier: Intended Audience :: Science/Research
Classifier: Programming Language :: Python :: 3
Classifier: Topic :: Scientific/Engineering :: Bio-Informatics
Classifier: Topic :: Scientific/Engineering :: Image Processing
Requires-Python: >=3.11
Requires-Dist: fsspec>=2024.9.0
Requires-Dist: matplotlib>=3.9.4
Requires-Dist: nd2>=0.8.1
Requires-Dist: numpy>=2.1.3
Requires-Dist: pandas>=2.2.3
Requires-Dist: pims>=0.7
Requires-Dist: platformdirs>=4.3.6
Requires-Dist: psutil>=6.1.1
Requires-Dist: pyimagej>=1.5.0
Requires-Dist: requests>=2.32.3
Requires-Dist: scikit-image>=0.24.0
Requires-Dist: scipy>=1.14.1
Requires-Dist: tifffile>=2025.3.13
Requires-Dist: tkinter-tooltip>=3.1.2
Requires-Dist: xarray>=2024.7
